odoo/addons/base_phone_cdr/README.rst
odoo/addons/base_phone_cdr/__init__.py
odoo/addons/base_phone_cdr/__manifest__.py
odoo/addons/base_phone_cdr/i18n/base_phone_cdr.pot
odoo/addons/base_phone_cdr/models/__init__.py
odoo/addons/base_phone_cdr/models/phone_cdr.py
odoo/addons/base_phone_cdr/models/res_partner.py
odoo/addons/base_phone_cdr/models/res_users.py
odoo/addons/base_phone_cdr/security/ir.model.access.csv
odoo/addons/base_phone_cdr/static/description/icon.png
odoo/addons/base_phone_cdr/view/phone_cdr_view.xml
odoo/addons/base_phone_cdr/view/res_partner_view.xml
odoo/addons/base_phone_cdr/view/res_users_view.xml
odoo12_addon_base_phone_cdr-12.0.1.0.0.99.dev3.dist-info/METADATA
odoo12_addon_base_phone_cdr-12.0.1.0.0.99.dev3.dist-info/WHEEL
odoo12_addon_base_phone_cdr-12.0.1.0.0.99.dev3.dist-info/top_level.txt
odoo12_addon_base_phone_cdr-12.0.1.0.0.99.dev3.dist-info/RECORD
